LICENSE
twitter_video_tools/__init__.py
twitter_video_tools/__main__.py
twitter_video_tools/monsnode_parser.py
twitter_video_tools/platform_video_downloader.py
twitter_video_tools/py.typed
twitter_video_tools/tests/__init__.py
twitter_video_tools/tests/test_monsnode_parser.py
twitter_video_tools/twitter_crawler.py
twitter_video_tools/twitter_video_tools.py
twitter_video_tools/utils/__init__.py
twitter_video_tools/utils/execute_parallel.py
twitter_video_tools/utils/url_validator.py
twitter_video_tools/utils/youtube_dl_wrapper.py
twitter_video_tools/video_downloader.py
twitter_video_tools-2023.4.15.dist-info/LICENSE
twitter_video_tools-2023.4.15.dist-info/METADATA
twitter_video_tools-2023.4.15.dist-info/WHEEL
twitter_video_tools-2023.4.15.dist-info/RECORD
