Metadata-Version: 2.1
Name: twitter-video-tools
Version: 2023.4.15
Summary: Twitter Video Tools is a multi-processing supported video downloader, supports videos from twitter (or specific user from twitter) && monsnode.
Home-page: https://github.com/code-yeongyu/twitter_video_tools
License: MIT
Keywords: crawler,parser,downloader,monsnode,twitter,youtube_dl
Requires-Python: >=3.9,<4.0
Classifier: Environment :: Console
Classifier: License :: OSI Approved :: MIT License
Classifier: Operating System :: OS Independent
Classifier: Programming Language :: Python :: 3
Classifier: Programming Language :: Python :: 3.9
Classifier: Programming Language :: Python :: 3.10
Classifier: Programming Language :: Python :: 3.11
Classifier: Topic :: Internet :: WWW/HTTP :: Browsers
Classifier: Topic :: Software Development :: Libraries :: Python Modules
Classifier: Topic :: Software Development :: Testing :: Unit
Classifier: Topic :: Software Development :: Version Control
Classifier: Typing :: Typed
Requires-Dist: bs4 (>=0.0.1,<0.0.2)
Requires-Dist: playwright (>=1.27.1,<2.0.0)
Requires-Dist: requests (>=2.28.1,<3.0.0)
Requires-Dist: typer[all] (>=0.7.0,<0.8.0)
Requires-Dist: yt-dlp (>=2022.11.11,<2023.0.0)
